mcp_server_builder/__init__.py
mcp_server_builder/config.py
mcp_server_builder/server.py
mcp_server_builder/tools/__init__.py
mcp_server_builder/tools/docs.py
mcp_server_builder/utils/__init__.py
mcp_server_builder/utils/cache.py
mcp_server_builder/utils/doc_fetcher.py
mcp_server_builder/utils/indexer.py
mcp_server_builder/utils/stopwords.py
mcp_server_builder/utils/text_processor.py
mcp_server_builder/utils/url_validator.py
mcp_server_builder-0.2.0.dist-info/METADATA
mcp_server_builder-0.2.0.dist-info/WHEEL
mcp_server_builder-0.2.0.dist-info/entry_points.txt
mcp_server_builder-0.2.0.dist-info/licenses/LICENSE
mcp_server_builder-0.2.0.dist-info/RECORD
