Metadata-Version: 2.4
Name: mcp-server-builder
Version: 0.2.0
Summary: MCP server for searching MCP protocol and FastMCP documentation
Project-URL: Homepage, https://github.com/praveenc/mcp-server-builder
Project-URL: Repository, https://github.com/praveenc/mcp-server-builder
Project-URL: Documentation, https://github.com/praveenc/mcp-server-builder#readme
Author-email: Praveen Chamarthi <1090396+praveenc@users.noreply.github.com>
License: MIT
License-File: LICENSE
Keywords: documentation,fastmcp,mcp,model-context-protocol,search
Classifier: Development Status :: 4 - Beta
Classifier: Intended Audience :: Developers
Classifier: License :: OSI Approved :: MIT License
Classifier: Operating System :: OS Independent
Classifier: Programming Language :: Python :: 3
Classifier: Programming Language :: Python :: 3.13
Classifier: Topic :: Documentation
Classifier: Topic :: Software Development :: Libraries
Requires-Python: >=3.13
Requires-Dist: fastmcp>=2.13.3
Requires-Dist: loguru>=0.7.3
Requires-Dist: mcp[cli]<1.23,>=1.21.1
Requires-Dist: nltk>=3.9.2
Requires-Dist: pydantic>=2.12.5
